paquete_demo
