Metadata-Version: 2.1
Name: paquete-demo
Version: 0.0.2
Summary: Paquete demo.
Home-page: https://bitbucket.org/ageabigdata/paquete_demo
Author: Usuario demo
Author-email: bigdata@agea.com.ar
License: MIT
Platform: UNKNOWN
